CHANGELOG
MANIFEST.in
README
distribute_setup.py
pkg_utils.py
setup.cfg
setup.py
doc/README
doc/conf.py
doc/index.rst
doc/libref.rst
doc/tutorial.rst
doc/_static/empty
doc/_templates/empty
modgrammar/__init__.py
modgrammar/extras.py
modgrammar/grammar_py2.py
modgrammar/grammar_py3.py
modgrammar/util.py
modgrammar_py2.egg-info/PKG-INFO
modgrammar_py2.egg-info/SOURCES.txt
modgrammar_py2.egg-info/dependency_links.txt
modgrammar_py2.egg-info/top_level.txt
modgrammar_py2.egg-info/zip-safe
tests/__init__.py
tests/__main__.py
tests/basic_grammar.py
tests/parsing.py
tests/regression.py
tests/util.py
tests/whitespace.py
tests/ref_tests/__init__.py
tests/ref_tests/basic_resolve_refs.py
tests/ref_tests/follow_norecurse_resolve_refs.py
tests/ref_tests/follow_resolve_refs.py
tests/ref_tests/general_tests.py
tests/ref_tests/norecurse_resolve_refs.py