Metadata-Version: 1.1
Name: modgrammar-py2
Version: 0.9.1
Summary: Modular grammar-parsing engine (Python 2.6+ / Python 3.x)
Home-page: http://code.google.com/p/modgrammar
Author: Alex Stewart, Aleksey Rembish
Author-email: alex@foogod.com, alex@rembish.ru
License: BSD
Download-URL: https://github.com/don-ramon/modgrammar-py2
Platform: any
Classifier: Development Status :: 4 - Beta
Classifier: Intended Audience :: Developers
Classifier: License :: OSI Approved :: BSD License
Classifier: Operating System :: OS Independent
Classifier: Programming Language :: Python
Classifier: Programming Language :: Python :: 2
Classifier: Programming Language :: Python :: 2.6
Classifier: Programming Language :: Python :: 2.7
Classifier: Programming Language :: Python :: 3
Classifier: Programming Language :: Python :: 3.1
Classifier: Programming Language :: Python :: 3.2
Classifier: Topic :: Text Processing
Classifier: Topic :: Software Development :: Libraries :: Python Modules
